literacy2/__init__.py
literacy2/lit2go.py
lit2go-0.0.6.dist-info/LICENSE
lit2go-0.0.6.dist-info/METADATA
lit2go-0.0.6.dist-info/WHEEL
lit2go-0.0.6.dist-info/entry_points.txt
lit2go-0.0.6.dist-info/top_level.txt
lit2go-0.0.6.dist-info/RECORD
